metamart_source_bigquery/__init__.py
metamart_source_bigquery/adapters.py
metamart_source_bigquery/base.py
metamart_source_bigquery/loader.py
metamart_source_bigquery/models.py
metamart_source_bigquery/package_definitions.py
metamart_source_bigquery-0.2.5.dist-info/METADATA
metamart_source_bigquery-0.2.5.dist-info/WHEEL
metamart_source_bigquery-0.2.5.dist-info/RECORD
