Metadata-Version: 2.1
Name: metamart_source_bigquery
Version: 0.2.5
Summary: 
Home-page: https://www.metamart.io/
License: Elastic-2.0
Author: Edward Louth
Author-email: edward@metamart.io
Requires-Python: >=3.8,<4.0
Classifier: License :: Other/Proprietary License
Classifier: Programming Language :: Python :: 3
Classifier: Programming Language :: Python :: 3.8
Classifier: Programming Language :: Python :: 3.9
Classifier: Programming Language :: Python :: 3.10
Classifier: Programming Language :: Python :: 3.11
Classifier: Programming Language :: Python :: 3.12
Requires-Dist: google-cloud-bigquery (>=3.5.0,<4.0.0)
Requires-Dist: google-cloud-logging (>=3.5.0,<4.0.0)
Requires-Dist: metamart-schemas (>=0.2.6,<0.3.0)
Requires-Dist: multimethod (>=1.8,<2.0,!=1.11)
Requires-Dist: pydantic (>=1.9.1,<2.0.0)
Requires-Dist: setuptools (>=67.1.0,<68.0.0)
Project-URL: Documentation, https://docs.metamart.io/
Project-URL: Repository, https://github.com/meta-mart/metamart-core/tree/master/metamart-integrations/source-bigquery
